{
    "base_files_url": "",
    "db_files": [],
    "db_id": "bgm",
    "db_url": "https://raw.githubusercontent.com/wizzomafizzo/MiSTer_BGM/main/bgm.json",
    "default_options": {},
    "files": {
        "Scripts/bgm.sh": {
            "hash": "c7be8c929f4fd2e7f73a3520692c577f",
            "size": 32056,
            "url": "https://raw.githubusercontent.com/wizzomafizzo/MiSTer_BGM/main/bgm.sh"
        }
    },
    "folders": {
        "Scripts": {}
    },
    "timestamp": 1672718157,
    "zips": {}
}